LICENSE
README.md
setup.cfg
setup.py
test/test_baseline.py
test/test_basenji.py
test/test_data.py
test/test_densenet.py
test/test_layers.py
test/test_lstm.py
test/test_resnet.py
test/test_utils.py
torchomics/__init__.py
torchomics/_version.py
torchomics/data.py
torchomics/layers.py
torchomics/losses.py
torchomics/transforms.py
torchomics/utils.py
torchomics.egg-info/PKG-INFO
torchomics.egg-info/SOURCES.txt
torchomics.egg-info/dependency_links.txt
torchomics.egg-info/requires.txt
torchomics.egg-info/top_level.txt